yhki7refef/__init__.py
yhki7refef/_version.py
yhki7refef/skeleton.py
yhki7refef-0.0.4.dist-info/METADATA
yhki7refef-0.0.4.dist-info/WHEEL
yhki7refef-0.0.4.dist-info/entry_points.txt
yhki7refef-0.0.4.dist-info/licenses/AUTHORS.md
yhki7refef-0.0.4.dist-info/licenses/LICENSE.txt
yhki7refef-0.0.4.dist-info/RECORD
