Metadata-Version: 2.4
Name: yhki7refef
Version: 0.0.4
Summary: Testing
Project-URL: Documentation, https://github.com/bartosz121/yhki7refef
Project-URL: Source, https://github.com/bartosz121/yhki7refef
Author-email: Bartosz Magiera <admin@bartoszmagiera.dev>
License: MIT
License-File: AUTHORS.md
License-File: LICENSE.txt
Keywords: keyword_1,keyword_2
Classifier: Development Status :: 2 - Pre-Alpha
Classifier: Programming Language :: Python
Classifier: Programming Language :: Python :: 3.10
Classifier: Programming Language :: Python :: 3.11
Classifier: Programming Language :: Python :: 3.12
Classifier: Programming Language :: Python :: Implementation :: CPython
Requires-Python: >=3.10
Requires-Dist: typer
